{
  "frameWidth": 312,
  "frameHeight": 149,
  "totalFrames": 37,
  "centerIndex": 18,
  "scale": "1x",
  "hybridNote": "L2-L13 left.png (correct occupants); L14-L19 flipped right.png",
  "pivotOffsets": [
    3,
    -13,
    -12,
    -41,
    -41,
    -32,
    -31,
    -29,
    -33,
    -36,
    -36,
    -25,
    -28,
    -3,
    -10,
    -9,
    -9,
    6,
    3,
    3,
    9,
    12,
    12,
    5,
    30,
    28,
    38,
    38,
    36,
    31,
    33,
    34,
    43,
    43,
    14,
    15,
    -2
  ],
  "frames": [
    {
      "index": 0,
      "name": "L19_90deg_left",
      "x": 0,
      "y": 0,
      "w": 312,
      "h": 149,
      "source": "right_flipped",
      "pivotOffsetX": 3
    },
    {
      "index": 1,
      "name": "L18_85deg_left",
      "x": 312,
      "y": 0,
      "w": 312,
      "h": 149,
      "source": "right_flipped",
      "pivotOffsetX": -13
    },
    {
      "index": 2,
      "name": "L17_80deg_left",
      "x": 624,
      "y": 0,
      "w": 312,
      "h": 149,
      "source": "right_flipped",
      "pivotOffsetX": -12
    },
    {
      "index": 3,
      "name": "L16_75deg_left",
      "x": 936,
      "y": 0,
      "w": 312,
      "h": 149,
      "source": "right_flipped",
      "pivotOffsetX": -41
    },
    {
      "index": 4,
      "name": "L15_70deg_left",
      "x": 1248,
      "y": 0,
      "w": 312,
      "h": 149,
      "source": "right_flipped",
      "pivotOffsetX": -41
    },
    {
      "index": 5,
      "name": "L14_65deg_left",
      "x": 1560,
      "y": 0,
      "w": 312,
      "h": 149,
      "source": "right_flipped",
      "pivotOffsetX": -32
    },
    {
      "index": 6,
      "name": "L13_60deg_left",
      "x": 1872,
      "y": 0,
      "w": 312,
      "h": 149,
      "source": "right_flipped_fallback",
      "pivotOffsetX": -31
    },
    {
      "index": 7,
      "name": "L12_55deg_left",
      "x": 2184,
      "y": 0,
      "w": 312,
      "h": 149,
      "source": "right_flipped_fallback",
      "pivotOffsetX": -29
    },
    {
      "index": 8,
      "name": "L11_50deg_left",
      "x": 2496,
      "y": 0,
      "w": 312,
      "h": 149,
      "source": "right_flipped_fallback",
      "pivotOffsetX": -33
    },
    {
      "index": 9,
      "name": "L10_45deg_left",
      "x": 2808,
      "y": 0,
      "w": 312,
      "h": 149,
      "source": "right_flipped_fallback",
      "pivotOffsetX": -36
    },
    {
      "index": 10,
      "name": "L9_40deg_left",
      "x": 3120,
      "y": 0,
      "w": 312,
      "h": 149,
      "source": "right_flipped_fallback",
      "pivotOffsetX": -36
    },
    {
      "index": 11,
      "name": "L8_35deg_left",
      "x": 3432,
      "y": 0,
      "w": 312,
      "h": 149,
      "source": "right_flipped_fallback",
      "pivotOffsetX": -25
    },
    {
      "index": 12,
      "name": "L7_30deg_left",
      "x": 3744,
      "y": 0,
      "w": 312,
      "h": 149,
      "source": "right_flipped_fallback",
      "pivotOffsetX": -28
    },
    {
      "index": 13,
      "name": "L6_25deg_left",
      "x": 4056,
      "y": 0,
      "w": 312,
      "h": 149,
      "source": "right_flipped_fallback",
      "pivotOffsetX": -3
    },
    {
      "index": 14,
      "name": "L5_20deg_left",
      "x": 4368,
      "y": 0,
      "w": 312,
      "h": 149,
      "source": "right_flipped_fallback",
      "pivotOffsetX": -10
    },
    {
      "index": 15,
      "name": "L4_15deg_left",
      "x": 4680,
      "y": 0,
      "w": 312,
      "h": 149,
      "source": "left_real",
      "pivotOffsetX": -9
    },
    {
      "index": 16,
      "name": "L3_10deg_left",
      "x": 4992,
      "y": 0,
      "w": 312,
      "h": 149,
      "source": "left_real",
      "pivotOffsetX": -9
    },
    {
      "index": 17,
      "name": "L2_5deg_left",
      "x": 5304,
      "y": 0,
      "w": 312,
      "h": 149,
      "source": "left_real",
      "pivotOffsetX": 6
    },
    {
      "index": 18,
      "name": "STRAIGHT_0deg",
      "x": 5616,
      "y": 0,
      "w": 312,
      "h": 149,
      "source": "shared",
      "pivotOffsetX": 3
    },
    {
      "index": 19,
      "name": "R2_5deg_right",
      "x": 5928,
      "y": 0,
      "w": 312,
      "h": 149,
      "source": "right_real",
      "pivotOffsetX": 3
    },
    {
      "index": 20,
      "name": "R3_10deg_right",
      "x": 6240,
      "y": 0,
      "w": 312,
      "h": 149,
      "source": "right_real",
      "pivotOffsetX": 9
    },
    {
      "index": 21,
      "name": "R4_15deg_right",
      "x": 6552,
      "y": 0,
      "w": 312,
      "h": 149,
      "source": "right_real",
      "pivotOffsetX": 12
    },
    {
      "index": 22,
      "name": "R5_20deg_right",
      "x": 6864,
      "y": 0,
      "w": 312,
      "h": 149,
      "source": "right_real",
      "pivotOffsetX": 12
    },
    {
      "index": 23,
      "name": "R6_25deg_right",
      "x": 7176,
      "y": 0,
      "w": 312,
      "h": 149,
      "source": "right_real",
      "pivotOffsetX": 5
    },
    {
      "index": 24,
      "name": "R7_30deg_right",
      "x": 7488,
      "y": 0,
      "w": 312,
      "h": 149,
      "source": "right_real",
      "pivotOffsetX": 30
    },
    {
      "index": 25,
      "name": "R8_35deg_right",
      "x": 7800,
      "y": 0,
      "w": 312,
      "h": 149,
      "source": "right_real",
      "pivotOffsetX": 28
    },
    {
      "index": 26,
      "name": "R9_40deg_right",
      "x": 8112,
      "y": 0,
      "w": 312,
      "h": 149,
      "source": "right_real",
      "pivotOffsetX": 38
    },
    {
      "index": 27,
      "name": "R10_45deg_right",
      "x": 8424,
      "y": 0,
      "w": 312,
      "h": 149,
      "source": "right_real",
      "pivotOffsetX": 38
    },
    {
      "index": 28,
      "name": "R11_50deg_right",
      "x": 8736,
      "y": 0,
      "w": 312,
      "h": 149,
      "source": "right_real",
      "pivotOffsetX": 36
    },
    {
      "index": 29,
      "name": "R12_55deg_right",
      "x": 9048,
      "y": 0,
      "w": 312,
      "h": 149,
      "source": "right_real",
      "pivotOffsetX": 31
    },
    {
      "index": 30,
      "name": "R13_60deg_right",
      "x": 9360,
      "y": 0,
      "w": 312,
      "h": 149,
      "source": "right_real",
      "pivotOffsetX": 33
    },
    {
      "index": 31,
      "name": "R14_65deg_right",
      "x": 9672,
      "y": 0,
      "w": 312,
      "h": 149,
      "source": "right_real",
      "pivotOffsetX": 34
    },
    {
      "index": 32,
      "name": "R15_70deg_right",
      "x": 9984,
      "y": 0,
      "w": 312,
      "h": 149,
      "source": "right_real",
      "pivotOffsetX": 43
    },
    {
      "index": 33,
      "name": "R16_75deg_right",
      "x": 10296,
      "y": 0,
      "w": 312,
      "h": 149,
      "source": "right_real",
      "pivotOffsetX": 43
    },
    {
      "index": 34,
      "name": "R17_80deg_right",
      "x": 10608,
      "y": 0,
      "w": 312,
      "h": 149,
      "source": "right_real",
      "pivotOffsetX": 14
    },
    {
      "index": 35,
      "name": "R18_85deg_right",
      "x": 10920,
      "y": 0,
      "w": 312,
      "h": 149,
      "source": "right_real",
      "pivotOffsetX": 15
    },
    {
      "index": 36,
      "name": "R19_90deg_right",
      "x": 11232,
      "y": 0,
      "w": 312,
      "h": 149,
      "source": "right_real",
      "pivotOffsetX": -2
    }
  ]
}